{
  "Name": "秘密の場所で 小咲",
  "Serial": "NK/W30-091",
  "Rarity": "C",
  "Expansion": "ニセコイ",
  "Side": "W",
  "Color": "Blue",
  "Level": 0,
  "Cost": 0,
  "Power": 1500,
  "Soul": 1,
  "Type": "Character",
  "FirstChara": "お菓子",
  "SecondChara": "鍵",
  "Text": "【永】 相手のターン中、相手のキャラが3枚以下なら、このカードのパワーを＋2000。\n【自】 記憶 ［(1)］ このカードが手札から舞台に置かれた時、あなたの思い出置場の「約束のペンダント」が2枚以上なら、あなたはコストを払ってよい。そうしたら、あなたは自分の山札を見て《鍵》のキャラを1枚まで選んで相手に見せ、手札に加え、その山札をシャッフルする。",
  "Flavor": "……今思えば、あれが私の初コイ\n……だったような気がするの\n",
  "Trigger": "None",
  "Image": "http://ws-tcg.com/cardlist/cardimages/nk_w30_091.gif"
}