{
  "Name": "風花＆ユノ",
  "Serial": "P3/S01-030",
  "Rarity": "R",
  "Expansion": "ペルソナ3",
  "Side": "S",
  "Color": "Green",
  "Level": 2,
  "Cost": 2,
  "Power": 4500,
  "Soul": 2,
  "Type": "Character",
  "FirstChara": "魔法",
  "SecondChara": "神",
  "Text": "【永】 アラーム このカードがクロックの１番上にあるなら、緑のあなたのキャラすべてに、パワーを＋1000。\n【自】 このカードがアタックした時、クライマックス置場に「切れない絆」があるなら、あなたは自分の山札の上から1枚を、ストック置場に置き、そのターン中、このカードのパワーを＋3000。",
  "Flavor": "お待たせしました！　オラクル発動します！",
  "Trigger": "OneSoul",
  "Image": "http://ws-tcg.com/cardlist/cardimages/p3_s01_030.gif"
}