{
  "Name": "“絶唱”響",
  "Serial": "SG/W27-007",
  "Rarity": "R",
  "Expansion": "戦姫絶唱シンフォギアG",
  "Side": "W",
  "Color": "Yellow",
  "Level": 1,
  "Cost": 1,
  "Power": 6500,
  "Soul": 1,
  "Type": "Character",
  "FirstChara": "音楽",
  "SecondChara": "",
  "Text": "【自】 このカードがアタックした時、クライマックス置場に「Superb Song Combination Arts」があり、他のあなたのカード名に「響」を含むキャラが4枚以上なら、そのターン中、このカードのパワーを＋3000し、相手は『【自】 アンコール』を使えない。（ルールによる『【自】 アンコール ［(3)］』も使えない）",
  "Flavor": "Gatrandis babel ziggurat edenal",
  "Trigger": "None",
  "Image": "http://ws-tcg.com/cardlist/cardimages/sg_w27_007.gif"
}