{
  "Name": "“スイーツ男子”チョロ松",
  "Serial": "OMS/S41-037",
  "Rarity": "R",
  "Expansion": "おそ松さん",
  "Side": "S",
  "Color": "Green",
  "Level": 3,
  "Cost": 2,
  "Power": 9000,
  "Soul": 2,
  "Type": "Character",
  "FirstChara": "６つ子",
  "SecondChara": "オタク",
  "Text": "【永】 あなたのストックが6枚以上なら、このカードのパワーを＋3000。\n【自】 このカードが手札から舞台に置かれた時、あなたは2枚まで引き、自分の手札を2枚選び、控え室に置き、自分の山札の上から1枚までを、ストック置場に置く。\n【自】［(2) 手札を1枚控え室に置く］ このカードのバトル相手が【リバース】した時、あなたはコストを払ってよい。そうしたら、あなたはそのキャラをクロック置場に置く。",
  "Flavor": "なにこれすげーうまいよ！",
  "Trigger": "OneSoul",
  "Image": "http://ws-tcg.com/cardlist/cardimages/oms_s41_037.gif"
}