{
  "Name": "“妹のために”ココア",
  "Serial": "GU/W44-039",
  "Rarity": "R",
  "Expansion": "ご注文はうさぎですか？？",
  "Side": "W",
  "Color": "Red",
  "Level": 3,
  "Cost": 2,
  "Power": 9500,
  "Soul": 2,
  "Type": "Character",
  "FirstChara": "ラビットハウス",
  "SecondChara": "パン",
  "Text": "【永】 あなたのクロック置場に「“笑顔になれる報告”ココア」があるなら、あなたの手札のこのカードのレベルを－1。\n【自】 このカードが手札から舞台に置かれた時、あなたは自分の控え室の、《ラビットハウス》か《パン》のキャラを1枚選び、手札に戻してよい。\n【自】［手札を1枚控え室に置く］ このカードがアタックした時、クライマックス置場に「もふもふハンター」があるなら、あなたはコストを払ってよい。そうしたら、あなたは自分の控え室の、《ラビットハウス》か《パン》のキャラを2枚まで選び、手札に戻し、次の相手のターンの終わりまで、このカードのパワーを＋1000。",
  "Flavor": "チノちゃんに合わせるから、無理に笑わなくてもいいからね\n",
  "Trigger": "OneSoul",
  "Image": "http://ws-tcg.com/cardlist/cardimages/gu_w44_039.gif"
}