{
  "Name": "“少し大胆な夏”チノ",
  "Serial": "GU/W44-P03",
  "Rarity": "PR",
  "Expansion": "PRカード【Wサイド】",
  "Side": "W",
  "Color": "Blue",
  "Level": 0,
  "Cost": 0,
  "Power": 1000,
  "Soul": 1,
  "Type": "Character",
  "FirstChara": "ラビットハウス",
  "SecondChara": "コーヒー",
  "Text": "【永】 相手のターン中、他のあなたの前列の中央の枠のキャラに、パワーを＋1000。\n【自】［(1)あなたの山札の上から1枚をクロック置場に置く］ このカードが手札から舞台に置かれた時、あなたはコストを払ってよい。そうしたら、あなたは1枚引く。",
  "Flavor": "つい勢いでお返しを…\n",
  "Trigger": "None",
  "Image": "http://ws-tcg.com/cardlist/cardimages/gu_w44_p03.gif"
}