{
  "Name": "悲しみに暮れるクラン",
  "Serial": "MF/S13-080",
  "Rarity": "R",
  "Expansion": "劇場版マクロスＦ",
  "Side": "S",
  "Color": "Blue",
  "Level": 1,
  "Cost": 1,
  "Power": 5500,
  "Soul": 1,
  "Type": "Character",
  "FirstChara": "パイロット",
  "SecondChara": "",
  "Text": "【自】 このカードがアタックした時、クライマックス置場に「奇跡の生還」があるなら、あなたは1枚引き、自分の手札を1枚選び、控え室に置き、そのターン中、このカードのパワーを＋1000。\n【自】 チェンジ ［(2)このカードを控え室に置く］ あなたのアンコールステップの始めに、このカードが【レスト】しているなら、あなたはコストを払ってよい。そうしたら、あなたは自分の控え室の「いつもの笑顔 クラン」を1枚選び、このカードがいた枠に置く。",
  "Flavor": "…ミシェル…\n",
  "Trigger": "None",
  "Image": "http://ws-tcg.com/cardlist/cardimages/mf_s13_080.gif"
}