{
  "Name": "しっかり者 ウタイ",
  "Serial": "AW/S43-071",
  "Rarity": "C",
  "Expansion": "アクセル・ワールド -インフィニット・バースト-",
  "Side": "S",
  "Color": "Red",
  "Level": 1,
  "Cost": 1,
  "Power": 1000,
  "Soul": 1,
  "Type": "Character",
  "FirstChara": "アバター",
  "SecondChara": "動物",
  "Text": "【自】［(1)］ あなたがこのカードの『助太刀』を使った時、あなたはコストを払ってよい。そうしたら、あなたは自分の控え室の「アーダー・メイデン」を1枚選び、手札に戻す。\n【起】【カウンター】 助太刀1500 レベル1 ［(1) 手札のこのカードを控え室に置く］ （あなたは自分のフロントアタックされているキャラを1枚選び、そのターン中、パワーを＋1500）",
  "Flavor": "ぴったりなのです\n",
  "Trigger": "OneSoul",
  "Image": "http://ws-tcg.com/cardlist/cardimages/aw_s43_071.gif"
}