{
  "Name": "“Kaleidoscope”美遊",
  "Serial": "PI/SE18-18",
  "Rarity": "R",
  "Expansion": "Fate/kaleid liner プリズマ☆イリヤ",
  "Side": "S",
  "Color": "Blue",
  "Level": 3,
  "Cost": 2,
  "Power": 10000,
  "Soul": 2,
  "Type": "Character",
  "FirstChara": "マスター",
  "SecondChara": "魔法",
  "Text": "【自】 このカードが手札から舞台に置かれた時か『チェンジ』で舞台に置かれた時、あなたは自分の山札を上からＸ枚まで見て、カードを1枚まで選び、手札に加える。残りのカードを控え室に置く。Ｘはあなたの《魔法》のキャラの枚数に等しい。\n【自】 あなたのクライマックス置場に「クラスカード セイバー」が置かれた時、前列にこのカードがいるなら、あなたは1枚引き、そのターン中、このカードのパワーを＋1500し、このカードは次の能力を得る。『【自】 このカードのバトル相手が【リバース】した時、あなたはそのキャラを山札の下に置いてよい。』",
  "Flavor": "初めてだったんだ…。私を友達って言ってくれた人…",
  "Trigger": "OneSoul",
  "Image": "http://ws-tcg.com/cardlist/cardimages/pi_se18_018.gif"
}