{
  "Name": "コワモテな園長先生",
  "Serial": "CS/S28-033",
  "Rarity": "U",
  "Expansion": "クレヨンしんちゃん",
  "Side": "S",
  "Color": "Green",
  "Level": 0,
  "Cost": 0,
  "Power": 500,
  "Soul": 1,
  "Type": "Character",
  "FirstChara": "先生",
  "SecondChara": "幼稚園",
  "Text": "【永】 他のあなたの《幼稚園》のキャラすべてに、パワーを＋500。\n【自】［(2)］ このカードが手札から舞台に置かれた時、あなたはコストを払ってよい。そうしたら、あなたは自分の山札を見て《幼稚園》のキャラを1枚まで選んで相手に見せ、手札に加え、その山札をシャッフルする。",
  "Flavor": "しんのすけ「組長先生はいつもと同じように怖い顔だし」",
  "Trigger": "None",
  "Image": "http://ws-tcg.com/cardlist/cardimages/cs_s28_033.gif"
}