{
  "Name": "姉妹でお風呂 小咲",
  "Serial": "NK/WE22-28",
  "Rarity": "C",
  "Expansion": "ニセコイ:",
  "Side": "W",
  "Color": "Blue",
  "Level": 0,
  "Cost": 0,
  "Power": 500,
  "Soul": 1,
  "Type": "Character",
  "FirstChara": "お菓子",
  "SecondChara": "鍵",
  "Text": "【自】 このカードが手札から舞台に置かれた時、あなたは自分の山札を上から2枚まで見て、山札の上に元の順番で置く。 \n【自】 絆／「店の看板娘 春」 ［(1)］ （このカードがプレイされて舞台に置かれた時、あなたはコストを払ってよい。そうしたら、あなたは自分の控え室の「店の看板娘 春」を1枚選び、手札に戻す）",
  "Flavor": "どこ……って言われると難しいけど……\n",
  "Trigger": "None",
  "Image": "http://ws-tcg.com/cardlist/cardimages/nk_we22_28.gif"
}