{
  "Name": "主従関係 忍野忍",
  "Serial": "NM/S24-002S",
  "Rarity": "SR",
  "Expansion": "偽物語",
  "Side": "S",
  "Color": "Yellow",
  "Level": 3,
  "Cost": 2,
  "Power": 10000,
  "Soul": 2,
  "Type": "Character",
  "FirstChara": "怪異",
  "SecondChara": "血",
  "Text": "【永】 経験 あなたのレベル置場のカードのレベルの合計が6以上なら、このカードのパワーを＋1000し、このカードは次の能力を得る。『【永】 このカードは相手の効果に選ばれない。』\n【自】 このカードが手札から舞台に置かれた時か『チェンジ』で舞台に置かれた時、あなたは自分のクロックの上から1枚を、控え室に置いてよい。",
  "Flavor": "SECRET",
  "Trigger": "OneSoul",
  "Image": "http://ws-tcg.com/cardlist/cardimages/dc_w00_00.gif"
}