{
  "Name": "実戦担当 阿良々木火憐",
  "Serial": "NM/S24-023SP",
  "Rarity": "SP",
  "Expansion": "偽物語",
  "Side": "S",
  "Color": "Green",
  "Level": 0,
  "Cost": 0,
  "Power": 1000,
  "Soul": 1,
  "Type": "Character",
  "FirstChara": "怪異",
  "SecondChara": "スポーツ",
  "Text": "【永】 他のあなたの前列の中央の枠のキャラに、パワーを＋500。\n【起】 集中 ［(1)］ あなたは自分の山札の上から4枚をめくり、控え室に置く。それらのカードのクライマックス1枚につき、あなたは自分のキャラを1枚選び、そのターン中、パワーを＋2000。",
  "Flavor": "SECRET",
  "Trigger": "None",
  "Image": "http://ws-tcg.com/cardlist/cardimages/dc_w00_00.gif"
}