{
  "Name": "“ご奉仕してあげる♪”西木野 真姫",
  "Serial": "LL/W36-088",
  "Rarity": "C",
  "Expansion": "ラブライブ！ feat.スクールアイドルフェスティバル Vol.2",
  "Side": "W",
  "Color": "Blue",
  "Level": 1,
  "Cost": 0,
  "Power": 4500,
  "Soul": 1,
  "Type": "Character",
  "FirstChara": "音楽",
  "SecondChara": "",
  "Text": "【永】 あなたの手札が6枚以上なら、このカードのパワーを＋1500。\n【自】 アンコール ［あなたの山札の上から1枚をクロック置場に置く］ （このカードが舞台から控え室に置かれた時、あなたはコストを払ってよい。そうしたら、このカードがいた枠に【レスト】して置く）",
  "Flavor": "メイドの格好だからって、あなたの言うこと何でも聞くわけじゃないから。分かってる？\n",
  "Trigger": "None",
  "Image": "http://ws-tcg.com/cardlist/cardimages/ll_w36_088.gif"
}