{
  "Name": "“天衣無縫”長曾我部 元親",
  "Serial": "SB/S06-T13",
  "Rarity": "TD",
  "Expansion": "2009年度トライアルデッキ【S】",
  "Side": "S",
  "Color": "Red",
  "Level": 2,
  "Cost": 2,
  "Power": 8000,
  "Soul": 2,
  "Type": "Character",
  "FirstChara": "武器",
  "SecondChara": "眼帯",
  "Text": "【永】 他のあなたの《武器》のキャラが3枚以上なら、このカードのパワーを＋1000。\n【自】 他のあなたの《眼帯》のキャラがアタックした時、そのターン中、このカードのパワーを＋1000。",
  "Flavor": "鬼にかなうヤツなんか、この世にいやしねえのさ",
  "Trigger": "OneSoul",
  "Image": "http://ws-tcg.com/cardlist/cardimages/sb_s06_t13.gif"
}