{
  "Name": "わかった気がする？ 戦場ヶ原ひたぎ",
  "Serial": "MG/S39-064",
  "Rarity": "C",
  "Expansion": "<物語>シリーズ セカンドシーズン",
  "Side": "S",
  "Color": "Red",
  "Level": 0,
  "Cost": 0,
  "Power": 500,
  "Soul": 1,
  "Type": "Character",
  "FirstChara": "怪異",
  "SecondChara": "",
  "Text": "【永】 応援 このカードの前のあなたのキャラすべてに、パワーを＋500。\n【自】 あなたか相手がレベルアップした時、あなたは自分のキャラを1枚選び、そのターン中、パワーを＋500。",
  "Flavor": "手料理を食べて相手の人となりがわかるなんて、\n某料理漫画みたいだけどね\n",
  "Trigger": "None",
  "Image": "http://ws-tcg.com/cardlist/cardimages/mg_s39_064.gif"
}