{
  "Name": "嗜虐の芸術家 キャスター",
  "Serial": "FZ/S17-088",
  "Rarity": "R",
  "Expansion": "Fate/Zero",
  "Side": "S",
  "Color": "Blue",
  "Level": 2,
  "Cost": 2,
  "Power": 8500,
  "Soul": 2,
  "Type": "Character",
  "FirstChara": "サーヴァント",
  "SecondChara": "本",
  "Text": "【自】［他のあなたの舞台のキャラを1枚控え室に置く］ このカードがアタックした時、クライマックス置場に青のクライマックスがあるなら、あなたはコストを払ってよい。そうしたら、次の相手のターンの終わりまで、このカードのパワーを＋2000。",
  "Flavor": "ご期待あれ、リュウノスケ。\n最高のCOOLをご覧に入れましょう\n",
  "Trigger": "OneSoul",
  "Image": "http://ws-tcg.com/cardlist/cardimages/fz_s17_088.gif"
}