{
  "Name": "観測手 キャル",
  "Serial": "PT/W07-108",
  "Rarity": "PR",
  "Expansion": "PRカード【Wサイド】",
  "Side": "W",
  "Color": "Yellow",
  "Level": 0,
  "Cost": 0,
  "Power": 2000,
  "Soul": 1,
  "Type": "Character",
  "FirstChara": "時計",
  "SecondChara": "",
  "Text": "【自】 このカードが手札から舞台に置かれた時、そのターン中、このカードのパワーを＋1500。\n【起】 集中 ［(1) あなたのキャラを2枚【レスト】する］ あなたは自分の山札の上から4枚をめくり、控え室に置く。それらのカードのクライマックス1枚につき、あなたは自分の山札を見て《武器》のキャラを1枚まで選んで相手に見せ、手札に加え、その山札をシャッフルする。",
  "Flavor": "あたしに見せて！　玲二がそいつを撃つところを！\n",
  "Trigger": "None",
  "Image": "http://ws-tcg.com/cardlist/cardimages/pt_w07_108.gif"
}