{"Name":"“きよしこの夜”園田 海未","Serial":"LL/W36-045","Rarity":"U","Expansion":"ラブライブ！ feat.スクールアイドルフェスティバル Vol.2","Side":"W","Color":"Red","Level":1,"Cost":1,"Power":6000,"Soul":1,"Type":"Character","FirstChara":"音楽","SecondChara":"","Text":"【永】 経験 あなたのレベル置場に「“Happy maker!”園田 海未」があるなら、このカードのパワーを＋1500。\n【自】 このカードのバトル相手が【リバース】した時、あなたのクライマックス置場に「秘めた想い」があるなら、あなたは自分の控え室のキャラを1枚選び、手札に戻してよい。","Flavor":"私がサンタに、ですか？　……行事をより楽しむためにも、事前に調べておく必要がありそうですね","Trigger":"None","Image":"http://ws-tcg.com/cardlist/cardimages/ll_w36_045.gif"}