{
  "Name": "妖精王の妃 アスナ",
  "Serial": "SAO/S26-007",
  "Rarity": "U",
  "Expansion": "ソードアート・オンライン Vol.2",
  "Side": "S",
  "Color": "Yellow",
  "Level": 0,
  "Cost": 0,
  "Power": 1000,
  "Soul": 1,
  "Type": "Character",
  "FirstChara": "アバター",
  "SecondChara": "武器",
  "Text": "【自】 絆／「二つの世界 キリト」 ［(1)］ （このカードがプレイされて舞台に置かれた時、あなたはコストを払ってよい。そうしたら、あなたは自分の控え室の「二つの世界 キリト」を1枚選び、手札に戻す）",
  "Flavor": "きっと……助けに来るわ\n",
  "Trigger": "None",
  "Image": "http://ws-tcg.com/cardlist/cardimages/sao_s26_007.gif"
}